{
	"type":9,
	"controllers":{
		"intimacy_system":{
		},
		"slot_opacity":{
		},
		"slot_color":{
		}
	},
	"motions":{
		"shake":[{
				"file":"Open"
			}],
		"idle":[{
				"file":"Stand"
			}],
		"tap":[{
				"file":"Click"
			},{
				"file":"Special01"
			},{
				"file":"Special02"
			}]
	},
	"options":{
		"edge_padding":false,
		"shader":"Skeleton-Straight-Alpha"
	},
	"skeleton":"Jiping03.skel",
	"atlases":[{
			"atlas":"Jiping03.atlas",
			"tex_names":["Jiping03","Jiping032","Jiping033"],
			"textures":["Jiping03.png","Jiping032.png","Jiping033.png"]
		}]
}