{
	"type":9,
	"controllers":{
		"intimacy_system":{
		},
		"slot_opacity":{
		},
		"slot_color":{
		}
	},
	"motions":{
		"shake":[{
				"file":"Open"
			}],
		"idle":[{
				"file":"Stand"
			}],
		"tap":[{
				"file":"Click"
			},{
				"file":"Special01"
			},{
				"file":"Special02"
			}]
	},
	"options":{
		"edge_padding":false,
		"shader":"Skeleton-Straight-Alpha"
	},
	"skeleton":"Daqiaoxiaoqiao01.skel",
	"atlases":[{
			"atlas":"Daqiaoxiaoqiao01.atlas",
			"tex_names":["Daqiaoxiaoqiao01","Daqiaoxiaoqiao012"],
			"textures":["Daqiaoxiaoqiao01.png","Daqiaoxiaoqiao012.png"]
		}]
}